jsmod.py
jsmod-0.0.2.dist-info/DESCRIPTION.rst
jsmod-0.0.2.dist-info/metadata.json
jsmod-0.0.2.dist-info/WHEEL
jsmod-0.0.2.dist-info/top_level.txt
jsmod-0.0.2.dist-info/METADATA
jsmod-0.0.2.dist-info/RECORD
