Metadata-Version: 2.0
Name: jsmod
Version: 0.0.2
Summary: Import JavaScript modules directly from Python code
Home-page: https://github.com/sciyoshi/jsmod/
Author: Samuel Cormier-Iijima
Author-email: sciyoshi@gmail.com
License: MIT
Keywords: pyv8 javascript jsmod import importhooks hook
Platform: UNKNOWN
Classifier: Development Status :: 3 - Alpha
Classifier: Intended Audience :: Developers
Classifier: License :: OSI Approved :: MIT License
Classifier: Programming Language :: Python :: 2
Classifier: Programming Language :: Python :: 2.6
Classifier: Programming Language :: Python :: 2.7
Classifier: Programming Language :: Python :: 3
Classifier: Programming Language :: Python :: 3.3
Classifier: Programming Language :: Python :: 3.4
Requires-Dist: pyv8 (>=1.0-dev)
